localization_utils/__init__.py
localization_utils/inset.py
localization_utils/lib.py
localization_utils/utils_p/__init__.py
localization_utils/utils_p/memory_normalizer/__init__.py
localization_utils/utils_p/memory_normalizer/headers.py
localization_utils-1.0rc2.dist-info/METADATA
localization_utils-1.0rc2.dist-info/WHEEL
localization_utils-1.0rc2.dist-info/RECORD
